llm_food/__init__.py
llm_food/app.py
llm_food/cli.py
llm_food/client.py
llm_food/config.py
llm_food/models.py
llm_food-0.1.3.dist-info/METADATA
llm_food-0.1.3.dist-info/WHEEL
llm_food-0.1.3.dist-info/entry_points.txt
llm_food-0.1.3.dist-info/top_level.txt
llm_food-0.1.3.dist-info/RECORD
