Metadata-Version: 2.4
Name: llm-food
Version: 0.1.3
Summary: Serving files for hungry LLMs
Author-email: Yusuf Sarıgöz <yusufsarigoz@gmail.com>
Project-URL: homepage, https://github.com/altaidevorg/llm-food
Project-URL: project, https://github.com/altaidevorg/llm-food
Project-URL: repository, https://github.com/altaidevorg/llm-food
Keywords: llm-food,pdf-to-markdown,text-extraction,rag,llm
Classifier: Intended Audience :: Developers
Classifier: License :: OSI Approved :: MIT License
Classifier: Programming Language :: Python :: 3.10
Classifier: Programming Language :: Python :: 3.11
Classifier: Programming Language :: Python :: 3.12
Classifier: Topic :: Software Development :: Libraries :: Python Modules
Requires-Python: >=3.10
Requires-Dist: httpx>=0.28.1
Requires-Dist: pydantic>=2.10.3
Provides-Extra: server
Requires-Dist: duckdb; extra == "server"
Requires-Dist: fastapi; extra == "server"
Requires-Dist: google-genai; extra == "server"
Requires-Dist: google-cloud-storage; extra == "server"
Requires-Dist: mammoth; extra == "server"
Requires-Dist: markdownify; extra == "server"
Requires-Dist: pdf2image; extra == "server"
Requires-Dist: pypdf2; extra == "server"
Requires-Dist: python-multipart; extra == "server"
Requires-Dist: python-pptx; extra == "server"
Requires-Dist: striprtf; extra == "server"
Requires-Dist: trafilatura; extra == "server"
Requires-Dist: uvicorn; extra == "server"
Provides-Extra: pymupdf
Requires-Dist: pymupdf4llm; extra == "pymupdf"
